<?xml version="1.0" encoding="utf-8" ?>
<dwsync>
<file name="bootstrap(legends-of).css" server="ftp.viaserie.tk//public_html/" local="131156613983966961" remote="131147634000000000" Dst="1" />
<file name="bootstrap(mr-robot).css" server="ftp.viaserie.tk//public_html/" local="131156614005568197" remote="131142413400000000" Dst="1" />
<file name="bootstrap(supernatural).css" server="ftp.viaserie.tk//public_html/" local="131156614107774043" remote="131135574000000000" Dst="1" />
<file name="bootstrap(the-originals).css" server="ftp.viaserie.tk//public_html/" local="131156614131415395" remote="131153583600000000" Dst="1" />
<file name="bootstrap(the-orinals).css" server="ftp.viaserie.tk//public_html/" local="131156614142976056" remote="131153597400000000" Dst="1" />
<file name="cont.css" server="ftp.viaserie.tk//public_html/" local="131169706458492512" remote="131169814200000000" Dst="1" />
<file name="gridcontato.css" server="ftp.viaserie.tk//public_html/" local="131156614240951660" remote="131137029600000000" Dst="1" />
<file name="simpleGridTemplate.css" server="ftp.viaserie.tk//public_html/" local="131156614324136418" remote="131136964200000000" Dst="1" />
<file name="bootstrap(big bang theory).css" server="ftp.viaserie.tk//public_html/" local="131156614345327630" remote="131135570400000000" Dst="1" />
<file name="bootstrap(mr-robot) eps.css" server="ftp.viaserie.tk//public_html/" local="131156617537880234" remote="131143330200000000" Dst="1" />
<file name="bootstrap(supernatural) esps.css" server="ftp.viaserie.tk//public_html/" local="131156617729091170" remote="131141500200000000" Dst="1" />
<file name="bootstrap(gotham).css" server="ftp.viaserie.tk//public_html/" local="131156642338738762" remote="131153493600000000" Dst="1" />
<file name="simpleGridTemplate.css" server="viaserie.tk//public_html/" local="131225324368328702" remote="131225251800000000" Dst="2" />
<file name="cont.css" server="viaserie.tk//public_html/" local="131185594323952041" remote="131185558200000000" Dst="1" />
<file name="bootstrap(big bang theory).css" server="viaserie.tk//public_html/" local="131218329425886939" remote="131193945600000000" Dst="2" />
<file name="bootstrap(gotham).css" server="viaserie.tk//public_html/" local="131228770266177199" remote="131228697600000000" Dst="2" />
<file name="bootstrap(legends-of).css" server="viaserie.tk//public_html/" local="131231295262540950" remote="131222637600000000" Dst="2" />
<file name="bootstrap(mr-robot) eps.css" server="viaserie.tk//public_html/" local="131214871356244439" remote="131214799200000000" Dst="2" />
<file name="bootstrap(mr-robot).css" server="viaserie.tk//public_html/" local="131214858731642353" remote="131214786000000000" Dst="2" />
<file name="bootstrap(supernatural) esps.css" server="viaserie.tk//public_html/" local="131225334023680956" remote="131225262000000000" Dst="2" />
<file name="bootstrap(supernatural).css" server="viaserie.tk//public_html/" local="131225334480967112" remote="131225262000000000" Dst="2" />
<file name="bootstrap(the-originals).css" server="viaserie.tk//public_html/" local="131156614131415395" remote="131170791000000000" Dst="1" />
<file name="bootstrap(the-orinals).css" server="viaserie.tk//public_html/" local="131156614142976056" remote="131170791000000000" Dst="1" />
<file name="gridcontato.css" server="viaserie.tk//public_html/" local="131156614240951660" remote="131170791000000000" Dst="1" />
<file name="inicio home.css" server="viaserie.tk//public_html/" local="131121542840000000" remote="131170791000000000" Dst="1" />
<file name="bootstrap(big bang theory).css" server="www.viaserie.tk" local="131156614345327630" remote="131172815400000000" Dst="1" />
<file name="bootstrap(gotham).css" server="www.viaserie.tk" local="131156642338738762" remote="131172816000000000" Dst="1" />
<file name="bootstrap(legends-of).css" server="www.viaserie.tk" local="131156613983966961" remote="131172816000000000" Dst="1" />
<file name="bootstrap(mr-robot) eps.css" server="www.viaserie.tk" local="131156617537880234" remote="131172816000000000" Dst="1" />
<file name="bootstrap(mr-robot).css" server="www.viaserie.tk" local="131156614005568197" remote="131172816000000000" Dst="1" />
<file name="bootstrap(legends) eps.css" server="viaserie.tk//public_html/" local="131222724328910584" remote="131222655000000000" Dst="2" />
<file name="bootstrap(stranger).css" server="viaserie.tk//public_html/" local="131184352026469683" remote="131184315600000000" Dst="1" />
<file name="bootstrap(stranger) eps.css" server="viaserie.tk//public_html/" local="131190704024897046" remote="131190667800000000" Dst="1" />
<file name="bootstrap(the-big) eps.css" server="viaserie.tk//public_html/" local="131218329414056263" remote="131202543600000000" Dst="2" />
<file name="simpleGridTemplate.css" server="viaserie.tk/public_html/" local="131284835581481238" remote="131284727400000000" Dst="2" />
<file name="bootstrap(the-originals).css" server="files.000webhost.com/public_html/" local="131450519498410741" remote="131439433200000000" Dst="1" />
<file name="simpleGridTemplate.css" server="files.000webhost.com/public_html/" local="131588916820000000" remote="131588010600000000" Dst="2" />
</dwsync>